mkdocs_plugin_epigraph/__init__.py
mkdocs_plugin_epigraph/css/epigraph.css
mkdocs_plugin_epigraph/plugin.py
mkdocs_epigraph-0.5.1.dist-info/LICENSE.md
mkdocs_epigraph-0.5.1.dist-info/METADATA
mkdocs_epigraph-0.5.1.dist-info/WHEEL
mkdocs_epigraph-0.5.1.dist-info/entry_points.txt
mkdocs_epigraph-0.5.1.dist-info/RECORD
